wmain/__init__.py
wmain/api/__init__.py
wmain/api/pan123.py
wmain/api/pan123.pyi
wmain/common/__init__.py
wmain/common/http/__init__.py
wmain/common/http/ua.py
wmain/common/http/url.py
wmain/common/logging.py
wmain/common/models.py
wmain/common/utils/__init__.py
wmain/common/utils/mutree.py
wmain/core/__init__.py
wmain/core/http/__init__.py
wmain/core/http/api.py
wmain/ext/__init__.py
wmain/ext/fastapi/__init__.py
wmain/ext/fastapi/middlewares/__init__.py
wmain/ext/fastapi/middlewares/log_middleware.py
wmain/mail/__init__.py
wmain/mail/email.py
wmain/mail/exceptions.py
wmain/mail/sender/__init__.py
wmain/mail/sender/client_brevo.py
wmain/mail/sender/ports/__init__.py
wmain/mail/sender/ports/smtp_sender_port.py
wmain/mail/sender/smtp_base.py
wmain/mail/sender/smtp_brevo.py
wmain-3.1.2.dist-info/METADATA
wmain-3.1.2.dist-info/WHEEL
wmain-3.1.2.dist-info/RECORD
