Metadata-Version: 2.4
Name: wmain
Version: 3.1.2
Summary: wmain
License: MIT
Author: wmain@wyn.wiki
Requires-Python: >=3.10,<4.0
Classifier: License :: OSI Approved :: MIT License
Classifier: Programming Language :: Python :: 3
Classifier: Programming Language :: Python :: 3.10
Classifier: Programming Language :: Python :: 3.11
Classifier: Programming Language :: Python :: 3.12
Classifier: Programming Language :: Python :: 3.13
Classifier: Programming Language :: Python :: 3.14
Requires-Dist: aiosmtplib (>=5.0.0,<6.0.0)
Requires-Dist: fastapi (>=0.124.0,<0.125.0)
Requires-Dist: pydantic (>=2.12.5,<3.0.0)
